Metadata-Version: 2.1
Name: grobid-client-python-pvp
Version: 0.0.2
Summary: grobid_client_python
Home-page: UNKNOWN
Author: kermitt2
License: LICENSE
Platform: UNKNOWN
License-File: LICENSE
Requires-Dist: requests
